<annotation>
  <folder></folder>
  <filename>000012.jpeg</filename>
  <source>
    <database>Unknown</database>
    <annotation>Unknown</annotation>
    <image>Unknown</image>
  </source>
  <size>
    <width>352</width>
    <height>288</height>
    <depth>3</depth>
  </size>
  <segmented>0</segmented>
  <object>
    <name>vehicle</name>
    <occluded>0</occluded>
    <bndbox>
      <xmin>18.50390625</xmin>
      <ymin>180.3740234375</ymin>
      <xmax>50.919490814208984</xmax>
      <ymax>200.7376594543457</ymax>
    </bndbox>
  </object>
  <object>
    <name>vehicle</name>
    <occluded>0</occluded>
    <bndbox>
      <xmin>63.0</xmin>
      <ymin>167.40000000000146</ymin>
      <xmax>84.70000000000073</xmax>
      <ymax>184.0</ymax>
    </bndbox>
  </object>
  <object>
    <name>vehicle</name>
    <occluded>0</occluded>
    <bndbox>
      <xmin>7.0</xmin>
      <ymin>199.900390625</ymin>
      <xmax>48.600000000000364</xmax>
      <ymax>219.00039062499854</ymax>
    </bndbox>
  </object>
</annotation>
