<annotation>
  <folder></folder>
  <filename>000861.jpeg</filename>
  <source>
    <database>Unknown</database>
    <annotation>Unknown</annotation>
    <image>Unknown</image>
  </source>
  <size>
    <width>352</width>
    <height>288</height>
    <depth>3</depth>
  </size>
  <segmented>0</segmented>
  <object>
    <name>vehicle</name>
    <occluded>0</occluded>
    <bndbox>
      <xmin>75.2607421875</xmin>
      <ymin>100.3154296875</ymin>
      <xmax>84.73159408569336</xmax>
      <ymax>108.06430912017822</ymax>
    </bndbox>
  </object>
  <object>
    <name>vehicle</name>
    <occluded>0</occluded>
    <bndbox>
      <xmin>102.0</xmin>
      <ymin>111.60000000000036</ymin>
      <xmax>114.20000000000073</xmax>
      <ymax>119.0</ymax>
    </bndbox>
  </object>
  <object>
    <name>vehicle</name>
    <occluded>0</occluded>
    <bndbox>
      <xmin>70.095703125</xmin>
      <ymin>99.884765625</ymin>
      <xmax>76.55310201644897</xmax>
      <ymax>105.05068492889404</ymax>
    </bndbox>
  </object>
</annotation>
