<annotation>
  <folder></folder>
  <filename>000922.jpeg</filename>
  <source>
    <database>Unknown</database>
    <annotation>Unknown</annotation>
    <image>Unknown</image>
  </source>
  <size>
    <width>352</width>
    <height>288</height>
    <depth>3</depth>
  </size>
  <segmented>0</segmented>
  <object>
    <name>vehicle</name>
    <occluded>0</occluded>
    <bndbox>
      <xmin>38.12109375</xmin>
      <ymin>126.26171875</ymin>
      <xmax>49.73892784118652</xmax>
      <ymax>138.4910182952881</ymax>
    </bndbox>
  </object>
  <object>
    <name>cyclist</name>
    <occluded>0</occluded>
    <bndbox>
      <xmin>18.0</xmin>
      <ymin>211.0</ymin>
      <xmax>34.0</xmax>
      <ymax>253.0</ymax>
    </bndbox>
  </object>
  <object>
    <name>vehicle</name>
    <occluded>0</occluded>
    <bndbox>
      <xmin>45.15234375</xmin>
      <ymin>138.796875</ymin>
      <xmax>61.05043315887451</xmax>
      <ymax>152.86056995391846</ymax>
    </bndbox>
  </object>
  <object>
    <name>vehicle</name>
    <occluded>0</occluded>
    <bndbox>
      <xmin>79.0</xmin>
      <ymin>178.0</ymin>
      <xmax>120.29999999999927</xmax>
      <ymax>213.0</ymax>
    </bndbox>
  </object>
  <object>
    <name>vehicle</name>
    <occluded>0</occluded>
    <bndbox>
      <xmin>49.79999999999927</xmin>
      <ymin>151.5</ymin>
      <xmax>70.0999984741211</xmax>
      <ymax>170.99960899353027</ymax>
    </bndbox>
  </object>
  <object>
    <name>vehicle</name>
    <occluded>0</occluded>
    <bndbox>
      <xmin>71.0</xmin>
      <ymin>137.8000000000011</ymin>
      <xmax>91.0</xmax>
      <ymax>154.0</ymax>
    </bndbox>
  </object>
  <object>
    <name>vehicle</name>
    <occluded>0</occluded>
    <bndbox>
      <xmin>102.93359375</xmin>
      <ymin>160.50390625</ymin>
      <xmax>134.4240379333496</xmax>
      <ymax>182.8223762512207</ymax>
    </bndbox>
  </object>
  <object>
    <name>vehicle</name>
    <occluded>0</occluded>
    <bndbox>
      <xmin>309.0</xmin>
      <ymin>243.0</ymin>
      <xmax>352.0</xmax>
      <ymax>272.0</ymax>
    </bndbox>
  </object>
  <object>
    <name>vehicle</name>
    <occluded>0</occluded>
    <bndbox>
      <xmin>45.45703125</xmin>
      <ymin>132.98828125</ymin>
      <xmax>61.04938793182373</xmax>
      <ymax>142.4659881591797</ymax>
    </bndbox>
  </object>
</annotation>
