<annotation>
  <folder></folder>
  <filename>001434.jpeg</filename>
  <source>
    <database>Unknown</database>
    <annotation>Unknown</annotation>
    <image>Unknown</image>
  </source>
  <size>
    <width>704</width>
    <height>480</height>
    <depth>3</depth>
  </size>
  <segmented>0</segmented>
  <object>
    <name>vehicle</name>
    <occluded>0</occluded>
    <bndbox>
      <xmin>542.2999999999993</xmin>
      <ymin>330.751953125</ymin>
      <xmax>600.0613784790039</xmax>
      <ymax>367.4491996765137</ymax>
    </bndbox>
  </object>
  <object>
    <name>vehicle</name>
    <occluded>0</occluded>
    <bndbox>
      <xmin>130.82421875</xmin>
      <ymin>283.291015625</ymin>
      <xmax>162.6284999847412</xmax>
      <ymax>304.3307704925537</ymax>
    </bndbox>
  </object>
  <object>
    <name>vehicle</name>
    <occluded>0</occluded>
    <bndbox>
      <xmin>579.51171875</xmin>
      <ymin>357.6640625</ymin>
      <xmax>650.4597320556641</xmax>
      <ymax>397.2970886230469</ymax>
    </bndbox>
  </object>
  <object>
    <name>vehicle</name>
    <occluded>0</occluded>
    <bndbox>
      <xmin>468.9296875</xmin>
      <ymin>276.9296875</ymin>
      <xmax>489.9694423675537</xmax>
      <ymax>293.5657730102539</ymax>
    </bndbox>
  </object>
  <object>
    <name>vehicle</name>
    <occluded>0</occluded>
    <bndbox>
      <xmin>415.59765625</xmin>
      <ymin>266.166015625</ymin>
      <xmax>432.7230396270752</xmax>
      <ymax>279.8663206100464</ymax>
    </bndbox>
  </object>
  <object>
    <name>vehicle</name>
    <occluded>0</occluded>
    <bndbox>
      <xmin>168.990234375</xmin>
      <ymin>282.2999999999993</ymin>
      <xmax>202.2624053955078</xmax>
      <ymax>304.81928634643555</ymax>
    </bndbox>
  </object>
  <object>
    <name>vehicle</name>
    <occluded>0</occluded>
    <bndbox>
      <xmin>65.75</xmin>
      <ymin>279.376953125</ymin>
      <xmax>100.49005889892578</xmax>
      <ymax>302.86319160461426</ymax>
    </bndbox>
  </object>
  <object>
    <name>vehicle</name>
    <occluded>0</occluded>
    <bndbox>
      <xmin>16.330078125</xmin>
      <ymin>289.65234375</ymin>
      <xmax>69.17411422729492</xmax>
      <ymax>309.7000000000007</ymax>
    </bndbox>
  </object>
  <object>
    <name>vehicle</name>
    <occluded>0</occluded>
    <bndbox>
      <xmin>35.412109375</xmin>
      <ymin>281.33203125</ymin>
      <xmax>63.79131507873535</xmax>
      <ymax>290.6286678314209</ymax>
    </bndbox>
  </object>
  <object>
    <name>vehicle</name>
    <occluded>0</occluded>
    <bndbox>
      <xmin>616.9000000000015</xmin>
      <ymin>377.90000000000146</ymin>
      <xmax>699.0</xmax>
      <ymax>432.0</ymax>
    </bndbox>
  </object>
  <object>
    <name>vehicle</name>
    <occluded>0</occluded>
    <bndbox>
      <xmin>486.1000000000022</xmin>
      <ymin>288.2000000000007</ymin>
      <xmax>517.0</xmax>
      <ymax>310.0</ymax>
    </bndbox>
  </object>
  <object>
    <name>vehicle</name>
    <occluded>0</occluded>
    <bndbox>
      <xmin>302.0</xmin>
      <ymin>251.90000000000146</ymin>
      <xmax>314.90000000000146</xmax>
      <ymax>260.0</ymax>
    </bndbox>
  </object>
</annotation>
