<annotation>
  <folder></folder>
  <filename>001717.jpeg</filename>
  <source>
    <database>Unknown</database>
    <annotation>Unknown</annotation>
    <image>Unknown</image>
  </source>
  <size>
    <width>352</width>
    <height>288</height>
    <depth>3</depth>
  </size>
  <segmented>0</segmented>
  <object>
    <name>vehicle</name>
    <occluded>0</occluded>
    <bndbox>
      <xmin>163.70000000000073</xmin>
      <ymin>142.20000000000073</ymin>
      <xmax>187.10078048706055</xmax>
      <ymax>155.1599998474121</ymax>
    </bndbox>
  </object>
  <object>
    <name>vehicle</name>
    <occluded>0</occluded>
    <bndbox>
      <xmin>256.0</xmin>
      <ymin>176.0</ymin>
      <xmax>291.0</xmax>
      <ymax>218.0</ymax>
    </bndbox>
  </object>
  <object>
    <name>vehicle</name>
    <occluded>0</occluded>
    <bndbox>
      <xmin>54.0</xmin>
      <ymin>175.0</ymin>
      <xmax>122.0</xmax>
      <ymax>211.0</ymax>
    </bndbox>
  </object>
  <object>
    <name>vehicle</name>
    <occluded>0</occluded>
    <bndbox>
      <xmin>296.0</xmin>
      <ymin>150.0</ymin>
      <xmax>337.0</xmax>
      <ymax>172.0</ymax>
    </bndbox>
  </object>
  <object>
    <name>pedestrian</name>
    <occluded>0</occluded>
    <bndbox>
      <xmin>312.98046875</xmin>
      <ymin>119.599609375</ymin>
      <xmax>320.58046865463257</xmax>
      <ymax>138.49960899353027</ymax>
    </bndbox>
  </object>
  <object>
    <name>vehicle</name>
    <occluded>0</occluded>
    <bndbox>
      <xmin>143.5</xmin>
      <ymin>136.66015625</ymin>
      <xmax>160.29999923706055</xmax>
      <ymax>148.16015625</ymax>
    </bndbox>
  </object>
  <object>
    <name>vehicle</name>
    <occluded>0</occluded>
    <bndbox>
      <xmin>110.900390625</xmin>
      <ymin>148.5595703125</ymin>
      <xmax>133.50039100646973</xmax>
      <ymax>167.5595703125</ymax>
    </bndbox>
  </object>
  <object>
    <name>vehicle</name>
    <occluded>0</occluded>
    <bndbox>
      <xmin>103.400390625</xmin>
      <ymin>144.4599609375</ymin>
      <xmax>120.00039100646973</xmax>
      <ymax>159.55996131896973</ymax>
    </bndbox>
  </object>
  <object>
    <name>vehicle</name>
    <occluded>0</occluded>
    <bndbox>
      <xmin>81.099609375</xmin>
      <ymin>145.5595703125</ymin>
      <xmax>101.79961013793945</xmax>
      <ymax>164.0595703125</ymax>
    </bndbox>
  </object>
  <object>
    <name>vehicle</name>
    <occluded>0</occluded>
    <bndbox>
      <xmin>99.7998046875</xmin>
      <ymin>136.4599609375</ymin>
      <xmax>110.49980449676514</xmax>
      <ymax>145.65996074676514</ymax>
    </bndbox>
  </object>
  <object>
    <name>vehicle</name>
    <occluded>0</occluded>
    <bndbox>
      <xmin>116.2001953125</xmin>
      <ymin>135.9599609375</ymin>
      <xmax>129.10019493103027</xmax>
      <ymax>146.9599609375</ymax>
    </bndbox>
  </object>
  <object>
    <name>vehicle</name>
    <occluded>0</occluded>
    <bndbox>
      <xmin>76.2001953125</xmin>
      <ymin>122.0595703125</ymin>
      <xmax>84.7001953125</xmax>
      <ymax>134.45956993103027</ymax>
    </bndbox>
  </object>
  <object>
    <name>vehicle</name>
    <occluded>0</occluded>
    <bndbox>
      <xmin>92.599609375</xmin>
      <ymin>131.5498046875</ymin>
      <xmax>102.49960899353027</xmax>
      <ymax>141.4598045349121</ymax>
    </bndbox>
  </object>
  <object>
    <name>vehicle</name>
    <occluded>0</occluded>
    <bndbox>
      <xmin>144.10000000000036</xmin>
      <ymin>146.10000000000036</ymin>
      <xmax>168.10293006896973</xmax>
      <ymax>162.77910232543945</ymax>
    </bndbox>
  </object>
  <object>
    <name>pedestrian</name>
    <occluded>0</occluded>
    <bndbox>
      <xmin>31.700000000000728</xmin>
      <ymin>176.90000000000146</ymin>
      <xmax>41.69980430603027</xmax>
      <ymax>192.59921836853027</ymax>
    </bndbox>
  </object>
</annotation>
