<annotation>
  <folder></folder>
  <filename>001827.jpeg</filename>
  <source>
    <database>Unknown</database>
    <annotation>Unknown</annotation>
    <image>Unknown</image>
  </source>
  <size>
    <width>352</width>
    <height>288</height>
    <depth>3</depth>
  </size>
  <segmented>0</segmented>
  <object>
    <name>vehicle</name>
    <occluded>0</occluded>
    <bndbox>
      <xmin>239.0</xmin>
      <ymin>72.0</ymin>
      <xmax>253.3000000000011</xmax>
      <ymax>84.0</ymax>
    </bndbox>
  </object>
  <object>
    <name>vehicle</name>
    <occluded>0</occluded>
    <bndbox>
      <xmin>0.0</xmin>
      <ymin>93.5703125</ymin>
      <xmax>17.049610137939453</xmax>
      <ymax>109.77031326293945</ymax>
    </bndbox>
  </object>
  <object>
    <name>vehicle</name>
    <occluded>0</occluded>
    <bndbox>
      <xmin>0.0</xmin>
      <ymin>107.76953125</ymin>
      <xmax>8.949609756469727</xmax>
      <ymax>125.46953201293945</ymax>
    </bndbox>
  </object>
  <object>
    <name>pedestrian</name>
    <occluded>0</occluded>
    <bndbox>
      <xmin>327.0</xmin>
      <ymin>193.0</ymin>
      <xmax>345.0</xmax>
      <ymax>241.0</ymax>
    </bndbox>
  </object>
</annotation>
