<annotation>
  <folder></folder>
  <filename>002297.jpeg</filename>
  <source>
    <database>Unknown</database>
    <annotation>Unknown</annotation>
    <image>Unknown</image>
  </source>
  <size>
    <width>704</width>
    <height>480</height>
    <depth>3</depth>
  </size>
  <segmented>0</segmented>
  <object>
    <name>vehicle</name>
    <occluded>0</occluded>
    <bndbox>
      <xmin>251.5205078125</xmin>
      <ymin>106.7568359375</ymin>
      <xmax>261.83195781707764</xmax>
      <ymax>116.05955791473389</ymax>
    </bndbox>
  </object>
  <object>
    <name>construction</name>
    <occluded>0</occluded>
    <bndbox>
      <xmin>526.0</xmin>
      <ymin>175.0</ymin>
      <xmax>537.8000000000011</xmax>
      <ymax>208.20000000000073</ymax>
    </bndbox>
  </object>
  <object>
    <name>construction</name>
    <occluded>0</occluded>
    <bndbox>
      <xmin>168.0</xmin>
      <ymin>180.0</ymin>
      <xmax>189.8000000000011</xmax>
      <ymax>228.0</ymax>
    </bndbox>
  </object>
  <object>
    <name>construction</name>
    <occluded>0</occluded>
    <bndbox>
      <xmin>258.5</xmin>
      <ymin>321.0</ymin>
      <xmax>290.3000000000011</xmax>
      <ymax>390.7000000000007</ymax>
    </bndbox>
  </object>
  <object>
    <name>vehicle</name>
    <occluded>0</occluded>
    <bndbox>
      <xmin>617.1630859375</xmin>
      <ymin>166.60546875</ymin>
      <xmax>695.1630859375</xmax>
      <ymax>189.40000000000146</ymax>
    </bndbox>
  </object>
  <object>
    <name>vehicle</name>
    <occluded>0</occluded>
    <bndbox>
      <xmin>0.0</xmin>
      <ymin>346.0</ymin>
      <xmax>27.0</xmax>
      <ymax>378.0</ymax>
    </bndbox>
  </object>
  <object>
    <name>construction</name>
    <occluded>0</occluded>
    <bndbox>
      <xmin>216.0</xmin>
      <ymin>250.0</ymin>
      <xmax>241.10000000000036</xmax>
      <ymax>321.3000000000011</ymax>
    </bndbox>
  </object>
  <object>
    <name>vehicle</name>
    <occluded>0</occluded>
    <bndbox>
      <xmin>209.2666015625</xmin>
      <ymin>110.0068359375</ymin>
      <xmax>218.68140411376953</xmax>
      <ymax>117.29209995269775</ymax>
    </bndbox>
  </object>
  <object>
    <name>construction</name>
    <occluded>0</occluded>
    <bndbox>
      <xmin>537.970703125</xmin>
      <ymin>174.5380859375</ymin>
      <xmax>551.5667543411255</xmax>
      <ymax>206.53335189819336</ymax>
    </bndbox>
  </object>
</annotation>
