<annotation>
  <folder></folder>
  <filename>002403.jpeg</filename>
  <source>
    <database>Unknown</database>
    <annotation>Unknown</annotation>
    <image>Unknown</image>
  </source>
  <size>
    <width>352</width>
    <height>288</height>
    <depth>3</depth>
  </size>
  <segmented>0</segmented>
  <object>
    <name>vehicle</name>
    <occluded>0</occluded>
    <bndbox>
      <xmin>291.115234375</xmin>
      <ymin>98.70000000000073</ymin>
      <xmax>308.0</xmax>
      <ymax>115.5146484375</ymax>
    </bndbox>
  </object>
  <object>
    <name>vehicle</name>
    <occluded>0</occluded>
    <bndbox>
      <xmin>300.857421875</xmin>
      <ymin>84.798828125</ymin>
      <xmax>315.91766262054443</xmax>
      <ymax>98.59010410308838</ymax>
    </bndbox>
  </object>
  <object>
    <name>construction</name>
    <occluded>0</occluded>
    <bndbox>
      <xmin>145.8154296875</xmin>
      <ymin>119.658203125</ymin>
      <xmax>190.2059555053711</xmax>
      <ymax>154.17125701904297</ymax>
    </bndbox>
  </object>
  <object>
    <name>construction</name>
    <occluded>0</occluded>
    <bndbox>
      <xmin>169.8701171875</xmin>
      <ymin>135.4619140625</ymin>
      <xmax>177.65588998794556</xmax>
      <ymax>156.8437385559082</ymax>
    </bndbox>
  </object>
  <object>
    <name>vehicle</name>
    <occluded>0</occluded>
    <bndbox>
      <xmin>61.6728515625</xmin>
      <ymin>112.10000000000036</ymin>
      <xmax>93.40000000000146</xmax>
      <ymax>131.837890625</ymax>
    </bndbox>
  </object>
  <object>
    <name>vehicle</name>
    <occluded>0</occluded>
    <bndbox>
      <xmin>104.794921875</xmin>
      <ymin>81.6591796875</ymin>
      <xmax>128.26844596862793</xmax>
      <ymax>93.62835311889648</ymax>
    </bndbox>
  </object>
  <object>
    <name>construction</name>
    <occluded>0</occluded>
    <bndbox>
      <xmin>144.0205078125</xmin>
      <ymin>132.8000000000011</ymin>
      <xmax>151.70000000000073</xmax>
      <ymax>152.3056640625</ymax>
    </bndbox>
  </object>
  <object>
    <name>vehicle</name>
    <occluded>0</occluded>
    <bndbox>
      <xmin>114.8134765625</xmin>
      <ymin>96.30000000000109</ymin>
      <xmax>144.10000000000036</xmax>
      <ymax>113.302734375</ymax>
    </bndbox>
  </object>
  <object>
    <name>vehicle</name>
    <occluded>0</occluded>
    <bndbox>
      <xmin>13.6904296875</xmin>
      <ymin>77.0107421875</ymin>
      <xmax>24.265135765075684</xmax>
      <ymax>82.70481491088867</ymax>
    </bndbox>
  </object>
  <object>
    <name>vehicle</name>
    <occluded>0</occluded>
    <bndbox>
      <xmin>0.0</xmin>
      <ymin>95.37109375</ymin>
      <xmax>9.041524887084961</xmax>
      <ymax>104.43512725830078</ymax>
    </bndbox>
  </object>
  <object>
    <name>construction</name>
    <occluded>0</occluded>
    <bndbox>
      <xmin>246.8125</xmin>
      <ymin>141.8000000000011</ymin>
      <xmax>256.5</xmax>
      <ymax>163.513671875</ymax>
    </bndbox>
  </object>
  <object>
    <name>vehicle</name>
    <occluded>0</occluded>
    <bndbox>
      <xmin>277.2548828125</xmin>
      <ymin>79.40000000000146</ymin>
      <xmax>292.0</xmax>
      <ymax>92.0</ymax>
    </bndbox>
  </object>
  <object>
    <name>construction</name>
    <occluded>0</occluded>
    <bndbox>
      <xmin>255.537109375</xmin>
      <ymin>133.1865234375</ymin>
      <xmax>293.1877136230469</xmax>
      <ymax>166.08199310302734</ymax>
    </bndbox>
  </object>
  <object>
    <name>vehicle</name>
    <occluded>0</occluded>
    <bndbox>
      <xmin>312.431640625</xmin>
      <ymin>71.1328125</ymin>
      <xmax>320.5195474624634</xmax>
      <ymax>77.12901973724365</ymax>
    </bndbox>
  </object>
  <object>
    <name>vehicle</name>
    <occluded>0</occluded>
    <bndbox>
      <xmin>307.271484375</xmin>
      <ymin>76.013671875</ymin>
      <xmax>317.3116445541382</xmax>
      <ymax>84.36652755737305</ymax>
    </bndbox>
  </object>
</annotation>
