<annotation>
  <folder></folder>
  <filename>002431.jpeg</filename>
  <source>
    <database>Unknown</database>
    <annotation>Unknown</annotation>
    <image>Unknown</image>
  </source>
  <size>
    <width>352</width>
    <height>288</height>
    <depth>3</depth>
  </size>
  <segmented>0</segmented>
  <object>
    <name>vehicle</name>
    <occluded>0</occluded>
    <bndbox>
      <xmin>177.01953125</xmin>
      <ymin>84.0703125</ymin>
      <xmax>184.31953144073486</xmax>
      <ymax>88.67031240463257</ymax>
    </bndbox>
  </object>
  <object>
    <name>vehicle</name>
    <occluded>0</occluded>
    <bndbox>
      <xmin>69.0</xmin>
      <ymin>131.0</ymin>
      <xmax>92.0</xmax>
      <ymax>147.0</ymax>
    </bndbox>
  </object>
  <object>
    <name>vehicle</name>
    <occluded>0</occluded>
    <bndbox>
      <xmin>0.0</xmin>
      <ymin>135.0</ymin>
      <xmax>21.0</xmax>
      <ymax>156.0</ymax>
    </bndbox>
  </object>
  <object>
    <name>pedestrian</name>
    <occluded>0</occluded>
    <bndbox>
      <xmin>2.708984375</xmin>
      <ymin>151.951171875</ymin>
      <xmax>8.867879390716553</xmax>
      <ymax>172.75196838378906</ymax>
    </bndbox>
  </object>
  <object>
    <name>vehicle</name>
    <occluded>0</occluded>
    <bndbox>
      <xmin>28.73828125</xmin>
      <ymin>125.3408203125</ymin>
      <xmax>47.4473762512207</xmax>
      <ymax>139.98272132873535</ymax>
    </bndbox>
  </object>
  <object>
    <name>vehicle</name>
    <occluded>0</occluded>
    <bndbox>
      <xmin>22.115234375</xmin>
      <ymin>124.0625</ymin>
      <xmax>35.01405143737793</xmax>
      <ymax>135.56685066223145</ymax>
    </bndbox>
  </object>
  <object>
    <name>vehicle</name>
    <occluded>0</occluded>
    <bndbox>
      <xmin>14.677734375</xmin>
      <ymin>120.34375</ymin>
      <xmax>27.22793483734131</xmax>
      <ymax>130.80225086212158</ymax>
    </bndbox>
  </object>
  <object>
    <name>vehicle</name>
    <occluded>0</occluded>
    <bndbox>
      <xmin>8.2861328125</xmin>
      <ymin>115.3466796875</ymin>
      <xmax>20.139100074768066</xmax>
      <ymax>125.80518054962158</ymax>
    </bndbox>
  </object>
  <object>
    <name>vehicle</name>
    <occluded>0</occluded>
    <bndbox>
      <xmin>0.0</xmin>
      <ymin>114.6494140625</ymin>
      <xmax>6.7760233879089355</xmax>
      <ymax>123.59724235534668</ymax>
    </bndbox>
  </object>
  <object>
    <name>vehicle</name>
    <occluded>0</occluded>
    <bndbox>
      <xmin>65.2998046875</xmin>
      <ymin>106.7802734375</ymin>
      <xmax>79.49980449676514</xmax>
      <ymax>115.18027305603027</ymax>
    </bndbox>
  </object>
  <object>
    <name>vehicle</name>
    <occluded>0</occluded>
    <bndbox>
      <xmin>74.599609375</xmin>
      <ymin>108.1796875</ymin>
      <xmax>92.89960861206055</xmax>
      <ymax>115.87968730926514</ymax>
    </bndbox>
  </object>
  <object>
    <name>vehicle</name>
    <occluded>0</occluded>
    <bndbox>
      <xmin>93.099609375</xmin>
      <ymin>109.8798828125</ymin>
      <xmax>114.39960861206055</xmax>
      <ymax>120.07988262176514</ymax>
    </bndbox>
  </object>
  <object>
    <name>vehicle</name>
    <occluded>0</occluded>
    <bndbox>
      <xmin>102.400390625</xmin>
      <ymin>111.7802734375</ymin>
      <xmax>126.50039100646973</xmax>
      <ymax>122.58027362823486</ymax>
    </bndbox>
  </object>
  <object>
    <name>vehicle</name>
    <occluded>0</occluded>
    <bndbox>
      <xmin>126.2001953125</xmin>
      <ymin>114.080078125</ymin>
      <xmax>155.60019493103027</xmax>
      <ymax>127.38007831573486</ymax>
    </bndbox>
  </object>
  <object>
    <name>vehicle</name>
    <occluded>0</occluded>
    <bndbox>
      <xmin>148.0</xmin>
      <ymin>115.98046875</ymin>
      <xmax>172.0</xmax>
      <ymax>130.58046913146973</ymax>
    </bndbox>
  </object>
  <object>
    <name>pedestrian</name>
    <occluded>0</occluded>
    <bndbox>
      <xmin>161.7998046875</xmin>
      <ymin>127.580078125</ymin>
      <xmax>165.89980459213257</xmax>
      <ymax>143.48007774353027</ymax>
    </bndbox>
  </object>
  <object>
    <name>vehicle</name>
    <occluded>0</occluded>
    <bndbox>
      <xmin>49.830078125</xmin>
      <ymin>91.5703125</ymin>
      <xmax>59.63007831573486</xmax>
      <ymax>96.97031259536743</ymax>
    </bndbox>
  </object>
  <object>
    <name>vehicle</name>
    <occluded>0</occluded>
    <bndbox>
      <xmin>70.9296875</xmin>
      <ymin>96.26953125</ymin>
      <xmax>79.9296875</xmax>
      <ymax>102.06953144073486</ymax>
    </bndbox>
  </object>
  <object>
    <name>vehicle</name>
    <occluded>0</occluded>
    <bndbox>
      <xmin>75.4296875</xmin>
      <ymin>92.26953125</ymin>
      <xmax>88.12968730926514</xmax>
      <ymax>97.46953105926514</ymax>
    </bndbox>
  </object>
  <object>
    <name>vehicle</name>
    <occluded>0</occluded>
    <bndbox>
      <xmin>97.23046875</xmin>
      <ymin>89.169921875</ymin>
      <xmax>107.03046894073486</xmax>
      <ymax>93.96992206573486</ymax>
    </bndbox>
  </object>
  <object>
    <name>vehicle</name>
    <occluded>0</occluded>
    <bndbox>
      <xmin>107.73046875</xmin>
      <ymin>90.4697265625</ymin>
      <xmax>118.23046875</xmax>
      <ymax>95.56972646713257</ymax>
    </bndbox>
  </object>
  <object>
    <name>vehicle</name>
    <occluded>0</occluded>
    <bndbox>
      <xmin>125.23046875</xmin>
      <ymin>90.90000000000146</ymin>
      <xmax>146.20000000000073</xmax>
      <ymax>103.06992197036743</ymax>
    </bndbox>
  </object>
  <object>
    <name>vehicle</name>
    <occluded>0</occluded>
    <bndbox>
      <xmin>151.4296875</xmin>
      <ymin>88.3203125</ymin>
      <xmax>161.02968788146973</xmax>
      <ymax>94.22031259536743</ymax>
    </bndbox>
  </object>
  <object>
    <name>vehicle</name>
    <occluded>0</occluded>
    <bndbox>
      <xmin>194.1298828125</xmin>
      <ymin>84.7197265625</ymin>
      <xmax>203.92988300323486</xmax>
      <ymax>91.41972637176514</ymax>
    </bndbox>
  </object>
  <object>
    <name>pedestrian</name>
    <occluded>0</occluded>
    <bndbox>
      <xmin>200.5302734375</xmin>
      <ymin>91.2197265625</ymin>
      <xmax>203.23027348518372</xmax>
      <ymax>97.31972646713257</ymax>
    </bndbox>
  </object>
  <object>
    <name>vehicle</name>
    <occluded>0</occluded>
    <bndbox>
      <xmin>199.4296875</xmin>
      <ymin>97.919921875</ymin>
      <xmax>217.4296875</xmax>
      <ymax>107.61992168426514</ymax>
    </bndbox>
  </object>
  <object>
    <name>pedestrian</name>
    <occluded>0</occluded>
    <bndbox>
      <xmin>254.650390625</xmin>
      <ymin>118.4501953125</ymin>
      <xmax>262.05039072036743</xmax>
      <ymax>137.25019454956055</ymax>
    </bndbox>
  </object>
  <object>
    <name>vehicle</name>
    <occluded>0</occluded>
    <bndbox>
      <xmin>256.75</xmin>
      <ymin>111.4501953125</ymin>
      <xmax>282.3500003814697</xmax>
      <ymax>124.25019550323486</ymax>
    </bndbox>
  </object>
  <object>
    <name>vehicle</name>
    <occluded>0</occluded>
    <bndbox>
      <xmin>279.8095703125</xmin>
      <ymin>113.740234375</ymin>
      <xmax>291.3095703125</xmax>
      <ymax>120.84023427963257</ymax>
    </bndbox>
  </object>
  <object>
    <name>vehicle</name>
    <occluded>0</occluded>
    <bndbox>
      <xmin>288.1904296875</xmin>
      <ymin>108.599609375</ymin>
      <xmax>304.49042892456055</xmax>
      <ymax>120.00960922241211</ymax>
    </bndbox>
  </object>
  <object>
    <name>vehicle</name>
    <occluded>0</occluded>
    <bndbox>
      <xmin>299.490234375</xmin>
      <ymin>108.599609375</ymin>
      <xmax>312.0902347564697</xmax>
      <ymax>118.89960956573486</ymax>
    </bndbox>
  </object>
  <object>
    <name>vehicle</name>
    <occluded>0</occluded>
    <bndbox>
      <xmin>303.1904296875</xmin>
      <ymin>106.900390625</ymin>
      <xmax>321.0904293060303</xmax>
      <ymax>116.70039081573486</ymax>
    </bndbox>
  </object>
  <object>
    <name>vehicle</name>
    <occluded>0</occluded>
    <bndbox>
      <xmin>346.3896484375</xmin>
      <ymin>101.7998046875</ymin>
      <xmax>352.0</xmax>
      <ymax>109.20980453491211</ymax>
    </bndbox>
  </object>
  <object>
    <name>vehicle</name>
    <occluded>0</occluded>
    <bndbox>
      <xmin>329.6904296875</xmin>
      <ymin>106.599609375</ymin>
      <xmax>344.49042987823486</xmax>
      <ymax>114.00960922241211</ymax>
    </bndbox>
  </object>
  <object>
    <name>vehicle</name>
    <occluded>0</occluded>
    <bndbox>
      <xmin>171.2958984375</xmin>
      <ymin>141.0</ymin>
      <xmax>216.70000000000073</xmax>
      <ymax>160.84765625</ymax>
    </bndbox>
  </object>
  <object>
    <name>vehicle</name>
    <occluded>0</occluded>
    <bndbox>
      <xmin>320.1806640625</xmin>
      <ymin>125.0</ymin>
      <xmax>350.5</xmax>
      <ymax>144.1044921875</ymax>
    </bndbox>
  </object>
  <object>
    <name>vehicle</name>
    <occluded>0</occluded>
    <bndbox>
      <xmin>31.2998046875</xmin>
      <ymin>135.400390625</ymin>
      <xmax>52.5</xmax>
      <ymax>150.40000000000146</ymax>
    </bndbox>
  </object>
  <object>
    <name>pedestrian</name>
    <occluded>0</occluded>
    <bndbox>
      <xmin>7.700000000000728</xmin>
      <ymin>163.3000000000011</ymin>
      <xmax>15.0</xmax>
      <ymax>187.0</ymax>
    </bndbox>
  </object>
  <object>
    <name>pedestrian</name>
    <occluded>0</occluded>
    <bndbox>
      <xmin>210.0078125</xmin>
      <ymin>129.1435546875</ymin>
      <xmax>217.40000000000146</xmax>
      <ymax>146.1435546875</ymax>
    </bndbox>
  </object>
  <object>
    <name>pedestrian</name>
    <occluded>0</occluded>
    <bndbox>
      <xmin>227.8720703125</xmin>
      <ymin>126.5595703125</ymin>
      <xmax>234.3000000000011</xmax>
      <ymax>139.5595703125</ymax>
    </bndbox>
  </object>
  <object>
    <name>pedestrian</name>
    <occluded>0</occluded>
    <bndbox>
      <xmin>192.0166015625</xmin>
      <ymin>127.4404296875</ymin>
      <xmax>199.0</xmax>
      <ymax>140.4404296875</ymax>
    </bndbox>
  </object>
  <object>
    <name>pedestrian</name>
    <occluded>0</occluded>
    <bndbox>
      <xmin>156.6005859375</xmin>
      <ymin>126.40000000000146</ymin>
      <xmax>161.40000000000146</xmax>
      <ymax>143.400390625</ymax>
    </bndbox>
  </object>
  <object>
    <name>construction</name>
    <occluded>0</occluded>
    <bndbox>
      <xmin>329.0</xmin>
      <ymin>152.0</ymin>
      <xmax>352.0</xmax>
      <ymax>181.70000000000073</ymax>
    </bndbox>
  </object>
</annotation>
