<annotation>
  <folder></folder>
  <filename>003056.jpeg</filename>
  <source>
    <database>Unknown</database>
    <annotation>Unknown</annotation>
    <image>Unknown</image>
  </source>
  <size>
    <width>704</width>
    <height>480</height>
    <depth>3</depth>
  </size>
  <segmented>0</segmented>
  <object>
    <name>vehicle</name>
    <occluded>0</occluded>
    <bndbox>
      <xmin>302.095703125</xmin>
      <ymin>198.7099609375</ymin>
      <xmax>314.53730297088623</xmax>
      <ymax>208.213960647583</ymax>
    </bndbox>
  </object>
  <object>
    <name>vehicle</name>
    <occluded>0</occluded>
    <bndbox>
      <xmin>274.7939453125</xmin>
      <ymin>212.87890625</ymin>
      <xmax>292.41954612731934</xmax>
      <ymax>225.14770603179932</ymax>
    </bndbox>
  </object>
  <object>
    <name>vehicle</name>
    <occluded>0</occluded>
    <bndbox>
      <xmin>259.068359375</xmin>
      <ymin>217.7177734375</ymin>
      <xmax>281.8779602050781</xmax>
      <ymax>232.5785732269287</ymax>
    </bndbox>
  </object>
  <object>
    <name>vehicle</name>
    <occluded>0</occluded>
    <bndbox>
      <xmin>246.28125</xmin>
      <ymin>226.5302734375</ymin>
      <xmax>269.4364490509033</xmax>
      <ymax>245.3654727935791</ymax>
    </bndbox>
  </object>
  <object>
    <name>vehicle</name>
    <occluded>0</occluded>
    <bndbox>
      <xmin>232.802734375</xmin>
      <ymin>232.7509765625</ymin>
      <xmax>260.10513496398926</xmax>
      <ymax>255.73337745666504</ymax>
    </bndbox>
  </object>
  <object>
    <name>vehicle</name>
    <occluded>0</occluded>
    <bndbox>
      <xmin>215.869140625</xmin>
      <ymin>243.2919921875</ymin>
      <xmax>247.49154090881348</xmax>
      <ymax>267.4839916229248</ymax>
    </bndbox>
  </object>
  <object>
    <name>vehicle</name>
    <occluded>0</occluded>
    <bndbox>
      <xmin>127.60000000000036</xmin>
      <ymin>238.7998046875</ymin>
      <xmax>157.11664390563965</xmax>
      <ymax>256.59820556640625</ymax>
    </bndbox>
  </object>
  <object>
    <name>vehicle</name>
    <occluded>0</occluded>
    <bndbox>
      <xmin>184.9375</xmin>
      <ymin>255.90625</ymin>
      <xmax>219.49750137329102</xmax>
      <ymax>280.8000000000011</ymax>
    </bndbox>
  </object>
  <object>
    <name>vehicle</name>
    <occluded>0</occluded>
    <bndbox>
      <xmin>159.8818359375</xmin>
      <ymin>267.484375</ymin>
      <xmax>202.73623657226562</xmax>
      <ymax>299.1067752838135</ymax>
    </bndbox>
  </object>
  <object>
    <name>vehicle</name>
    <occluded>0</occluded>
    <bndbox>
      <xmin>100.265625</xmin>
      <ymin>260.7451171875</ymin>
      <xmax>148.82242584228516</xmax>
      <ymax>285.8011169433594</ymax>
    </bndbox>
  </object>
  <object>
    <name>vehicle</name>
    <occluded>0</occluded>
    <bndbox>
      <xmin>114.939453125</xmin>
      <ymin>281.9931640625</ymin>
      <xmax>172.66905212402344</xmax>
      <ymax>320.7003631591797</ymax>
    </bndbox>
  </object>
  <object>
    <name>vehicle</name>
    <occluded>0</occluded>
    <bndbox>
      <xmin>465.12890625</xmin>
      <ymin>199.62109375</ymin>
      <xmax>501.6632308959961</xmax>
      <ymax>243.7058448791504</ymax>
    </bndbox>
  </object>
  <object>
    <name>vehicle</name>
    <occluded>0</occluded>
    <bndbox>
      <xmin>447.0</xmin>
      <ymin>239.599609375</ymin>
      <xmax>472.20000076293945</xmax>
      <ymax>256.99960937499964</ymax>
    </bndbox>
  </object>
  <object>
    <name>vehicle</name>
    <occluded>0</occluded>
    <bndbox>
      <xmin>414.4990234375</xmin>
      <ymin>192.40000000000146</ymin>
      <xmax>424.40000000000146</xmax>
      <ymax>201.2001953125</ymax>
    </bndbox>
  </object>
  <object>
    <name>vehicle</name>
    <occluded>0</occluded>
    <bndbox>
      <xmin>430.5</xmin>
      <ymin>213.0</ymin>
      <xmax>449.0</xmax>
      <ymax>226.5</ymax>
    </bndbox>
  </object>
  <object>
    <name>vehicle</name>
    <occluded>0</occluded>
    <bndbox>
      <xmin>291.3828125</xmin>
      <ymin>187.3046875</ymin>
      <xmax>300.3684129714966</xmax>
      <ymax>194.21668767929077</ymax>
    </bndbox>
  </object>
  <object>
    <name>vehicle</name>
    <occluded>0</occluded>
    <bndbox>
      <xmin>311.9453125</xmin>
      <ymin>194.7353515625</ymin>
      <xmax>323.00451278686523</xmax>
      <ymax>203.72095203399658</ymax>
    </bndbox>
  </object>
  <object>
    <name>vehicle</name>
    <occluded>0</occluded>
    <bndbox>
      <xmin>273.4111328125</xmin>
      <ymin>197.154296875</ymin>
      <xmax>290.3455333709717</xmax>
      <ymax>208.38629722595215</ymax>
    </bndbox>
  </object>
  <object>
    <name>vehicle</name>
    <occluded>0</occluded>
    <bndbox>
      <xmin>260.796875</xmin>
      <ymin>195.25390625</ymin>
      <xmax>272.5472745895386</xmax>
      <ymax>203.72110652923584</ymax>
    </bndbox>
  </object>
  <object>
    <name>vehicle</name>
    <occluded>0</occluded>
    <bndbox>
      <xmin>246.1083984375</xmin>
      <ymin>200.2646484375</ymin>
      <xmax>258.3771982192993</xmax>
      <ymax>204.06624841690063</ymax>
    </bndbox>
  </object>
  <object>
    <name>vehicle</name>
    <occluded>0</occluded>
    <bndbox>
      <xmin>250.0830078125</xmin>
      <ymin>191.4521484375</ymin>
      <xmax>260.9694080352783</xmax>
      <ymax>199.573748588562</ymax>
    </bndbox>
  </object>
  <object>
    <name>vehicle</name>
    <occluded>0</occluded>
    <bndbox>
      <xmin>276.521484375</xmin>
      <ymin>186.958984375</ymin>
      <xmax>291.5550842285156</xmax>
      <ymax>195.77178478240967</ymax>
    </bndbox>
  </object>
  <object>
    <name>vehicle</name>
    <occluded>0</occluded>
    <bndbox>
      <xmin>427.6904296875</xmin>
      <ymin>200.3203125</ymin>
      <xmax>439.2904300689697</xmax>
      <ymax>209.02031230926514</ymax>
    </bndbox>
  </object>
  <object>
    <name>vehicle</name>
    <occluded>0</occluded>
    <bndbox>
      <xmin>310.736328125</xmin>
      <ymin>185.75</ymin>
      <xmax>319.37632846832275</xmax>
      <ymax>192.31640005111694</ymax>
    </bndbox>
  </object>
  <object>
    <name>vehicle</name>
    <occluded>0</occluded>
    <bndbox>
      <xmin>67.80000000000109</xmin>
      <ymin>301.599609375</ymin>
      <xmax>138.4000015258789</xmax>
      <ymax>346.99999847412073</ymax>
    </bndbox>
  </object>
  <object>
    <name>vehicle</name>
    <occluded>0</occluded>
    <bndbox>
      <xmin>63.30000000000109</xmin>
      <ymin>242.0</ymin>
      <xmax>103.0</xmax>
      <ymax>265.0</ymax>
    </bndbox>
  </object>
  <object>
    <name>vehicle</name>
    <occluded>0</occluded>
    <bndbox>
      <xmin>299.158203125</xmin>
      <ymin>189.896484375</ymin>
      <xmax>310.73580265045166</xmax>
      <ymax>197.15408420562744</ymax>
    </bndbox>
  </object>
  <object>
    <name>vehicle</name>
    <occluded>0</occluded>
    <bndbox>
      <xmin>265.634765625</xmin>
      <ymin>187.99609375</ymin>
      <xmax>276.0027656555176</xmax>
      <ymax>193.3528938293457</ymax>
    </bndbox>
  </object>
  <object>
    <name>vehicle</name>
    <occluded>0</occluded>
    <bndbox>
      <xmin>514.4000000000015</xmin>
      <ymin>328.7001953125</ymin>
      <xmax>577.0</xmax>
      <ymax>374.0001953124993</ymax>
    </bndbox>
  </object>
  <object>
    <name>vehicle</name>
    <occluded>0</occluded>
    <bndbox>
      <xmin>0.0</xmin>
      <ymin>343.0</ymin>
      <xmax>51.0</xmax>
      <ymax>415.0</ymax>
    </bndbox>
  </object>
  <object>
    <name>vehicle</name>
    <occluded>0</occluded>
    <bndbox>
      <xmin>0.0</xmin>
      <ymin>289.0</ymin>
      <xmax>50.0</xmax>
      <ymax>332.0</ymax>
    </bndbox>
  </object>
  <object>
    <name>vehicle</name>
    <occluded>0</occluded>
    <bndbox>
      <xmin>543.0</xmin>
      <ymin>278.0</ymin>
      <xmax>585.0</xmax>
      <ymax>310.0</ymax>
    </bndbox>
  </object>
  <object>
    <name>vehicle</name>
    <occluded>0</occluded>
    <bndbox>
      <xmin>290.8642578125</xmin>
      <ymin>201.9931640625</ymin>
      <xmax>307.45305824279785</xmax>
      <ymax>215.64436435699463</ymax>
    </bndbox>
  </object>
  <object>
    <name>vehicle</name>
    <occluded>0</occluded>
    <bndbox>
      <xmin>242.48046875</xmin>
      <ymin>203.720703125</ymin>
      <xmax>263.7348690032959</xmax>
      <ymax>220.65510368347168</ymax>
    </bndbox>
  </object>
  <object>
    <name>vehicle</name>
    <occluded>0</occluded>
    <bndbox>
      <xmin>216.5595703125</xmin>
      <ymin>198.8828125</ymin>
      <xmax>233.6667709350586</xmax>
      <ymax>209.5964126586914</ymax>
    </bndbox>
  </object>
  <object>
    <name>vehicle</name>
    <occluded>0</occluded>
    <bndbox>
      <xmin>207.919921875</xmin>
      <ymin>210.8056640625</ymin>
      <xmax>230.03832244873047</xmax>
      <ymax>225.32086372375488</ymax>
    </bndbox>
  </object>
  <object>
    <name>vehicle</name>
    <occluded>0</occluded>
    <bndbox>
      <xmin>162.8193359375</xmin>
      <ymin>214.953125</ymin>
      <xmax>191.33133506774902</xmax>
      <ymax>229.12272453308105</ymax>
    </bndbox>
  </object>
  <object>
    <name>vehicle</name>
    <occluded>0</occluded>
    <bndbox>
      <xmin>170.9404296875</xmin>
      <ymin>222.2109375</ymin>
      <xmax>193.92283058166504</xmax>
      <ymax>240.18213844299316</ymax>
    </bndbox>
  </object>
  <object>
    <name>vehicle</name>
    <occluded>0</occluded>
    <bndbox>
      <xmin>188.3935546875</xmin>
      <ymin>229.4677734375</ymin>
      <xmax>216.55995559692383</xmax>
      <ymax>249.85817337036133</ymax>
    </bndbox>
  </object>
</annotation>
