<annotation>
  <folder></folder>
  <filename>003581.jpeg</filename>
  <source>
    <database>Unknown</database>
    <annotation>Unknown</annotation>
    <image>Unknown</image>
  </source>
  <size>
    <width>704</width>
    <height>480</height>
    <depth>3</depth>
  </size>
  <segmented>0</segmented>
  <object>
    <name>vehicle</name>
    <occluded>0</occluded>
    <bndbox>
      <xmin>83.2275390625</xmin>
      <ymin>148.046875</ymin>
      <xmax>107.39829635620117</xmax>
      <ymax>169.19628715515137</ymax>
    </bndbox>
  </object>
  <object>
    <name>vehicle</name>
    <occluded>0</occluded>
    <bndbox>
      <xmin>46.0</xmin>
      <ymin>153.0</ymin>
      <xmax>69.0</xmax>
      <ymax>171.0</ymax>
    </bndbox>
  </object>
  <object>
    <name>vehicle</name>
    <occluded>0</occluded>
    <bndbox>
      <xmin>191.0</xmin>
      <ymin>173.0</ymin>
      <xmax>233.0</xmax>
      <ymax>196.0</ymax>
    </bndbox>
  </object>
  <object>
    <name>vehicle</name>
    <occluded>0</occluded>
    <bndbox>
      <xmin>229.0</xmin>
      <ymin>223.0</ymin>
      <xmax>318.0</xmax>
      <ymax>279.0</ymax>
    </bndbox>
  </object>
  <object>
    <name>vehicle</name>
    <occluded>0</occluded>
    <bndbox>
      <xmin>127.8505859375</xmin>
      <ymin>182.2119140625</ymin>
      <xmax>165.50119018554688</xmax>
      <ymax>208.00954818725586</ymax>
    </bndbox>
  </object>
  <object>
    <name>vehicle</name>
    <occluded>0</occluded>
    <bndbox>
      <xmin>104.376953125</xmin>
      <ymin>161.9912109375</ymin>
      <xmax>141.330322265625</xmax>
      <ymax>191.5074234008789</ymax>
    </bndbox>
  </object>
  <object>
    <name>vehicle</name>
    <occluded>0</occluded>
    <bndbox>
      <xmin>88.3408203125</xmin>
      <ymin>153.392578125</ymin>
      <xmax>116.69497680664062</xmax>
      <ymax>178.72539138793945</ymax>
    </bndbox>
  </object>
  <object>
    <name>vehicle</name>
    <occluded>0</occluded>
    <bndbox>
      <xmin>66.7265625</xmin>
      <ymin>132.2431640625</ymin>
      <xmax>85.0870418548584</xmax>
      <ymax>148.74435424804688</ymax>
    </bndbox>
  </object>
  <object>
    <name>vehicle</name>
    <occluded>0</occluded>
    <bndbox>
      <xmin>81.1357421875</xmin>
      <ymin>127.8271484375</ymin>
      <xmax>96.24246501922607</xmax>
      <ymax>139.44770431518555</ymax>
    </bndbox>
  </object>
  <object>
    <name>vehicle</name>
    <occluded>0</occluded>
    <bndbox>
      <xmin>79.9736328125</xmin>
      <ymin>147.349609375</ymin>
      <xmax>95.54517841339111</xmax>
      <ymax>162.9211549758911</ymax>
    </bndbox>
  </object>
  <object>
    <name>vehicle</name>
    <occluded>0</occluded>
    <bndbox>
      <xmin>577.0</xmin>
      <ymin>288.0</ymin>
      <xmax>704.0</xmax>
      <ymax>373.10000000000036</ymax>
    </bndbox>
  </object>
  <object>
    <name>vehicle</name>
    <occluded>0</occluded>
    <bndbox>
      <xmin>155.0</xmin>
      <ymin>197.40000000000146</ymin>
      <xmax>205.0</xmax>
      <ymax>229.0</ymax>
    </bndbox>
  </object>
</annotation>
