<annotation>
  <folder></folder>
  <filename>003690.jpeg</filename>
  <source>
    <database>Unknown</database>
    <annotation>Unknown</annotation>
    <image>Unknown</image>
  </source>
  <size>
    <width>704</width>
    <height>480</height>
    <depth>3</depth>
  </size>
  <segmented>0</segmented>
  <object>
    <name>vehicle</name>
    <occluded>0</occluded>
    <bndbox>
      <xmin>229.0146484375</xmin>
      <ymin>411.8916015625</ymin>
      <xmax>326.7825622558594</xmax>
      <ymax>480.0</ymax>
    </bndbox>
  </object>
  <object>
    <name>construction</name>
    <occluded>0</occluded>
    <bndbox>
      <xmin>681.400390625</xmin>
      <ymin>312.5</ymin>
      <xmax>704.0</xmax>
      <ymax>362.0</ymax>
    </bndbox>
  </object>
  <object>
    <name>vehicle</name>
    <occluded>0</occluded>
    <bndbox>
      <xmin>606.0</xmin>
      <ymin>135.0</ymin>
      <xmax>669.9000000000015</xmax>
      <ymax>193.0</ymax>
    </bndbox>
  </object>
  <object>
    <name>vehicle</name>
    <occluded>0</occluded>
    <bndbox>
      <xmin>376.119140625</xmin>
      <ymin>165.7841796875</ymin>
      <xmax>397.1135139465332</xmax>
      <ymax>190.27761459350586</ymax>
    </bndbox>
  </object>
  <object>
    <name>vehicle</name>
    <occluded>0</occluded>
    <bndbox>
      <xmin>281.64453125</xmin>
      <ymin>193.5712890625</ymin>
      <xmax>333.5129814147949</xmax>
      <ymax>231.44348907470703</ymax>
    </bndbox>
  </object>
  <object>
    <name>construction</name>
    <occluded>0</occluded>
    <bndbox>
      <xmin>239.326171875</xmin>
      <ymin>316.099609375</ymin>
      <xmax>277.6100273132324</xmax>
      <ymax>408.9276657104492</ymax>
    </bndbox>
  </object>
  <object>
    <name>vehicle</name>
    <occluded>0</occluded>
    <bndbox>
      <xmin>346.3564453125</xmin>
      <ymin>228.623046875</ymin>
      <xmax>455.23902130126953</xmax>
      <ymax>268.5535202026367</ymax>
    </bndbox>
  </object>
  <object>
    <name>bus</name>
    <occluded>0</occluded>
    <bndbox>
      <xmin>436.10000000000036</xmin>
      <ymin>224.177734375</ymin>
      <xmax>574.8046493530273</xmax>
      <ymax>306.0969543457031</ymax>
    </bndbox>
  </object>
  <object>
    <name>construction</name>
    <occluded>0</occluded>
    <bndbox>
      <xmin>606.9130859375</xmin>
      <ymin>239.8203125</ymin>
      <xmax>634.9055824279785</xmax>
      <ymax>291.07128143310547</ymax>
    </bndbox>
  </object>
  <object>
    <name>construction</name>
    <occluded>0</occluded>
    <bndbox>
      <xmin>598.474609375</xmin>
      <ymin>265.548828125</ymin>
      <xmax>610.6184129714966</xmax>
      <ymax>307.94922637939453</ymax>
    </bndbox>
  </object>
  <object>
    <name>construction</name>
    <occluded>0</occluded>
    <bndbox>
      <xmin>634.9052734375</xmin>
      <ymin>248.46484375</ymin>
      <xmax>648.4898672103882</xmax>
      <ymax>288.18949127197266</ymax>
    </bndbox>
  </object>
  <object>
    <name>construction</name>
    <occluded>0</occluded>
    <bndbox>
      <xmin>605.6787109375</xmin>
      <ymin>272.958984375</ymin>
      <xmax>621.1157493591309</xmax>
      <ymax>315.56521224975586</ymax>
    </bndbox>
  </object>
  <object>
    <name>construction</name>
    <occluded>0</occluded>
    <bndbox>
      <xmin>621.3212890625</xmin>
      <ymin>277.28125</ymin>
      <xmax>640.6690444946289</xmax>
      <ymax>324.6215019226074</ymax>
    </bndbox>
  </object>
  <object>
    <name>vehicle</name>
    <occluded>0</occluded>
    <bndbox>
      <xmin>642.7275390625</xmin>
      <ymin>287.1611328125</ymin>
      <xmax>658.1645774841309</xmax>
      <ymax>327.7090873718262</ymax>
    </bndbox>
  </object>
  <object>
    <name>construction</name>
    <occluded>0</occluded>
    <bndbox>
      <xmin>676.6884765625</xmin>
      <ymin>305.0673828125</ymin>
      <xmax>692.948823928833</xmax>
      <ymax>352.6134605407715</ymax>
    </bndbox>
  </object>
  <object>
    <name>vehicle</name>
    <occluded>0</occluded>
    <bndbox>
      <xmin>603.826171875</xmin>
      <ymin>328.1201171875</ymin>
      <xmax>678.3000000000011</xmax>
      <ymax>396.0430908203125</ymax>
    </bndbox>
  </object>
  <object>
    <name>vehicle</name>
    <occluded>0</occluded>
    <bndbox>
      <xmin>494.8000000000011</xmin>
      <ymin>289.630859375</ymin>
      <xmax>607.5306701660156</xmax>
      <ymax>423.83018493652344</ymax>
    </bndbox>
  </object>
  <object>
    <name>vehicle</name>
    <occluded>0</occluded>
    <bndbox>
      <xmin>424.9619140625</xmin>
      <ymin>302.1865234375</ymin>
      <xmax>495.3548126220703</xmax>
      <ymax>361.05309677124023</ymax>
    </bndbox>
  </object>
  <object>
    <name>vehicle</name>
    <occluded>0</occluded>
    <bndbox>
      <xmin>405.8203125</xmin>
      <ymin>314.5361328125</ymin>
      <xmax>480.7414093017578</xmax>
      <ymax>374.0201873779297</ymax>
    </bndbox>
  </object>
  <object>
    <name>vehicle</name>
    <occluded>0</occluded>
    <bndbox>
      <xmin>366.9189453125</xmin>
      <ymin>323.38671875</ymin>
      <xmax>461.3936233520508</xmax>
      <ymax>370.7269706726074</ymax>
    </bndbox>
  </object>
  <object>
    <name>vehicle</name>
    <occluded>0</occluded>
    <bndbox>
      <xmin>365.68359375</xmin>
      <ymin>335.94140625</ymin>
      <xmax>464.4806442260742</xmax>
      <ymax>412.50911712646484</ymax>
    </bndbox>
  </object>
  <object>
    <name>vehicle</name>
    <occluded>0</occluded>
    <bndbox>
      <xmin>350.041015625</xmin>
      <ymin>363.111328125</ymin>
      <xmax>431.3427505493164</xmax>
      <ymax>421.97790145874023</ymax>
    </bndbox>
  </object>
  <object>
    <name>vehicle</name>
    <occluded>0</occluded>
    <bndbox>
      <xmin>298.810546875</xmin>
      <ymin>370.232421875</ymin>
      <xmax>402.54744720458984</xmax>
      <ymax>419.4251174926758</ymax>
    </bndbox>
  </object>
  <object>
    <name>vehicle</name>
    <occluded>0</occluded>
    <bndbox>
      <xmin>488.1513671875</xmin>
      <ymin>361.4638671875</ymin>
      <xmax>570.2764129638672</xmax>
      <ymax>434.5325164794922</ymax>
    </bndbox>
  </object>
  <object>
    <name>vehicle</name>
    <occluded>0</occluded>
    <bndbox>
      <xmin>453.9833984375</xmin>
      <ymin>372.1669921875</ymin>
      <xmax>559.1610870361328</xmax>
      <ymax>452.2337646484375</ymax>
    </bndbox>
  </object>
  <object>
    <name>vehicle</name>
    <occluded>0</occluded>
    <bndbox>
      <xmin>448.6318359375</xmin>
      <ymin>400.16015625</ymin>
      <xmax>548.6638488769531</xmax>
      <ymax>473.8462905883789</ymax>
    </bndbox>
  </object>
  <object>
    <name>vehicle</name>
    <occluded>0</occluded>
    <bndbox>
      <xmin>433.1953125</xmin>
      <ymin>430.0048828125</ymin>
      <xmax>515.7320098876953</xmax>
      <ymax>480.0</ymax>
    </bndbox>
  </object>
  <object>
    <name>vehicle</name>
    <occluded>0</occluded>
    <bndbox>
      <xmin>319.7841796875</xmin>
      <ymin>417.44921875</ymin>
      <xmax>448.6319885253906</xmax>
      <ymax>480.0</ymax>
    </bndbox>
  </object>
  <object>
    <name>vehicle</name>
    <occluded>0</occluded>
    <bndbox>
      <xmin>296.525390625</xmin>
      <ymin>395.837890625</ymin>
      <xmax>373.2989273071289</xmax>
      <ymax>421.154634475708</ymax>
    </bndbox>
  </object>
  <object>
    <name>vehicle</name>
    <occluded>0</occluded>
    <bndbox>
      <xmin>262.564453125</xmin>
      <ymin>404.6884765625</ymin>
      <xmax>336.2505874633789</xmax>
      <ymax>452.0287284851074</ymax>
    </bndbox>
  </object>
  <object>
    <name>construction</name>
    <occluded>0</occluded>
    <bndbox>
      <xmin>664.3000000000011</xmin>
      <ymin>248.0</ymin>
      <xmax>686.0</xmax>
      <ymax>272.0</ymax>
    </bndbox>
  </object>
  <object>
    <name>vehicle</name>
    <occluded>0</occluded>
    <bndbox>
      <xmin>209.2548828125</xmin>
      <ymin>438.0322265625</ymin>
      <xmax>305.78783416748047</xmax>
      <ymax>480.0</ymax>
    </bndbox>
  </object>
  <object>
    <name>vehicle</name>
    <occluded>0</occluded>
    <bndbox>
      <xmin>128.365234375</xmin>
      <ymin>449.7646484375</ymin>
      <xmax>270.59181213378906</xmax>
      <ymax>480.0</ymax>
    </bndbox>
  </object>
  <object>
    <name>vehicle</name>
    <occluded>0</occluded>
    <bndbox>
      <xmin>80.8193359375</xmin>
      <ymin>439.6787109375</ymin>
      <xmax>198.14083099365234</xmax>
      <ymax>477.34508514404297</ymax>
    </bndbox>
  </object>
  <object>
    <name>vehicle</name>
    <occluded>0</occluded>
    <bndbox>
      <xmin>0.0</xmin>
      <ymin>445.853515625</ymin>
      <xmax>109.22321319580078</xmax>
      <ymax>480.0</ymax>
    </bndbox>
  </object>
  <object>
    <name>construction</name>
    <occluded>0</occluded>
    <bndbox>
      <xmin>647.599609375</xmin>
      <ymin>295.599609375</ymin>
      <xmax>665.9996093749996</xmax>
      <ymax>329.3000000000011</ymax>
    </bndbox>
  </object>
</annotation>
