<annotation>
  <folder></folder>
  <filename>005262.jpeg</filename>
  <source>
    <database>Unknown</database>
    <annotation>Unknown</annotation>
    <image>Unknown</image>
  </source>
  <size>
    <width>704</width>
    <height>480</height>
    <depth>3</depth>
  </size>
  <segmented>0</segmented>
  <object>
    <name>vehicle</name>
    <occluded>0</occluded>
    <bndbox>
      <xmin>432.10000000000036</xmin>
      <ymin>119.0</ymin>
      <xmax>454.99999809265137</xmax>
      <ymax>128.40000000000146</ymax>
    </bndbox>
  </object>
  <object>
    <name>vehicle</name>
    <occluded>0</occluded>
    <bndbox>
      <xmin>189.0</xmin>
      <ymin>118.0</ymin>
      <xmax>248.20000000000073</xmax>
      <ymax>137.40000000000146</ymax>
    </bndbox>
  </object>
  <object>
    <name>vehicle</name>
    <occluded>0</occluded>
    <bndbox>
      <xmin>515.8525390625</xmin>
      <ymin>118.75</ymin>
      <xmax>529.725962638855</xmax>
      <ymax>125.36407375335693</ymax>
    </bndbox>
  </object>
  <object>
    <name>vehicle</name>
    <occluded>0</occluded>
    <bndbox>
      <xmin>158.0</xmin>
      <ymin>356.0</ymin>
      <xmax>312.0</xmax>
      <ymax>462.0</ymax>
    </bndbox>
  </object>
  <object>
    <name>vehicle</name>
    <occluded>0</occluded>
    <bndbox>
      <xmin>625.7001953125</xmin>
      <ymin>153.0</ymin>
      <xmax>637.1000000000004</xmax>
      <ymax>162.0</ymax>
    </bndbox>
  </object>
  <object>
    <name>vehicle</name>
    <occluded>0</occluded>
    <bndbox>
      <xmin>609.0</xmin>
      <ymin>148.40000000000146</ymin>
      <xmax>616.8000000000011</xmax>
      <ymax>157.0</ymax>
    </bndbox>
  </object>
  <object>
    <name>vehicle</name>
    <occluded>0</occluded>
    <bndbox>
      <xmin>84.2509765625</xmin>
      <ymin>118.1484375</ymin>
      <xmax>134.1488380432129</xmax>
      <ymax>129.29879760742188</ymax>
    </bndbox>
  </object>
  <object>
    <name>vehicle</name>
    <occluded>0</occluded>
    <bndbox>
      <xmin>578.6000000000004</xmin>
      <ymin>138.3000000000011</ymin>
      <xmax>585.0999999046326</xmax>
      <ymax>143.2999997138977</ymax>
    </bndbox>
  </object>
  <object>
    <name>vehicle</name>
    <occluded>0</occluded>
    <bndbox>
      <xmin>577.033203125</xmin>
      <ymin>158.5107421875</ymin>
      <xmax>591.8207664489746</xmax>
      <ymax>169.60141468048096</ymax>
    </bndbox>
  </object>
  <object>
    <name>vehicle</name>
    <occluded>0</occluded>
    <bndbox>
      <xmin>584.986328125</xmin>
      <ymin>153.5810546875</ymin>
      <xmax>597.8694324493408</xmax>
      <ymax>163.55145645141602</ymax>
    </bndbox>
  </object>
  <object>
    <name>vehicle</name>
    <occluded>0</occluded>
    <bndbox>
      <xmin>506.0</xmin>
      <ymin>188.5</ymin>
      <xmax>538.5</xmax>
      <ymax>212.0</ymax>
    </bndbox>
  </object>
  <object>
    <name>vehicle</name>
    <occluded>0</occluded>
    <bndbox>
      <xmin>483.1044921875</xmin>
      <ymin>119.8955078125</ymin>
      <xmax>501.9787998199463</xmax>
      <ymax>126.50958156585693</ymax>
    </bndbox>
  </object>
  <object>
    <name>vehicle</name>
    <occluded>0</occluded>
    <bndbox>
      <xmin>266.810546875</xmin>
      <ymin>91.109375</ymin>
      <xmax>396.7401123046875</xmax>
      <ymax>132.36570739746094</ymax>
    </bndbox>
  </object>
  <object>
    <name>vehicle</name>
    <occluded>0</occluded>
    <bndbox>
      <xmin>609.7451171875</xmin>
      <ymin>142.1552734375</ymin>
      <xmax>615.7945747375488</xmax>
      <ymax>147.3085150718689</ymax>
    </bndbox>
  </object>
  <object>
    <name>vehicle</name>
    <occluded>0</occluded>
    <bndbox>
      <xmin>536.728515625</xmin>
      <ymin>175.2705078125</ymin>
      <xmax>562.2814254760742</xmax>
      <ymax>195.48053741455078</ymax>
    </bndbox>
  </object>
  <object>
    <name>vehicle</name>
    <occluded>0</occluded>
    <bndbox>
      <xmin>444.123046875</xmin>
      <ymin>105.3974609375</ymin>
      <xmax>473.2254867553711</xmax>
      <ymax>121.78849029541016</ymax>
    </bndbox>
  </object>
  <object>
    <name>vehicle</name>
    <occluded>0</occluded>
    <bndbox>
      <xmin>127.73828125</xmin>
      <ymin>115.6396484375</ymin>
      <xmax>164.25571060180664</xmax>
      <ymax>127.34752655029297</ymax>
    </bndbox>
  </object>
  <object>
    <name>vehicle</name>
    <occluded>0</occluded>
    <bndbox>
      <xmin>134.427734375</xmin>
      <ymin>118.1484375</ymin>
      <xmax>182.09552383422852</xmax>
      <ymax>129.29879760742188</ymax>
    </bndbox>
  </object>
  <object>
    <name>vehicle</name>
    <occluded>0</occluded>
    <bndbox>
      <xmin>582.7001953125</xmin>
      <ymin>173.0</ymin>
      <xmax>606.9000000000015</xmax>
      <ymax>192.0</ymax>
    </bndbox>
  </object>
  <object>
    <name>vehicle</name>
    <occluded>0</occluded>
    <bndbox>
      <xmin>621.8994140625</xmin>
      <ymin>166.0</ymin>
      <xmax>639.9994140624985</xmax>
      <ymax>179.8000000000011</ymax>
    </bndbox>
  </object>
  <object>
    <name>vehicle</name>
    <occluded>0</occluded>
    <bndbox>
      <xmin>593.1640625</xmin>
      <ymin>139.4658203125</ymin>
      <xmax>600.8939251899719</xmax>
      <ymax>144.6190619468689</ymax>
    </bndbox>
  </object>
  <object>
    <name>vehicle</name>
    <occluded>0</occluded>
    <bndbox>
      <xmin>533.4365234375</xmin>
      <ymin>116.9912109375</ymin>
      <xmax>546.3420333862305</xmax>
      <ymax>124.41187906265259</ymax>
    </bndbox>
  </object>
  <object>
    <name>vehicle</name>
    <occluded>0</occluded>
    <bndbox>
      <xmin>586.3000000000011</xmin>
      <ymin>146.63671875</ymin>
      <xmax>596.1887216567993</xmax>
      <ymax>155.26279735565186</ymax>
    </bndbox>
  </object>
  <object>
    <name>vehicle</name>
    <occluded>0</occluded>
    <bndbox>
      <xmin>585.2109375</xmin>
      <ymin>141.7060546875</ymin>
      <xmax>592.9408001899719</xmax>
      <ymax>146.97132349014282</ymax>
    </bndbox>
  </object>
</annotation>
