<annotation>
  <folder></folder>
  <filename>006691.jpeg</filename>
  <source>
    <database>Unknown</database>
    <annotation>Unknown</annotation>
    <image>Unknown</image>
  </source>
  <size>
    <width>704</width>
    <height>480</height>
    <depth>3</depth>
  </size>
  <segmented>0</segmented>
  <object>
    <name>pedestrian</name>
    <occluded>0</occluded>
    <bndbox>
      <xmin>345.0</xmin>
      <ymin>151.90000000000146</ymin>
      <xmax>353.0</xmax>
      <ymax>167.201171875</ymax>
    </bndbox>
  </object>
  <object>
    <name>construction</name>
    <occluded>0</occluded>
    <bndbox>
      <xmin>295.0</xmin>
      <ymin>194.5</ymin>
      <xmax>305.0</xmax>
      <ymax>208.0</ymax>
    </bndbox>
  </object>
  <object>
    <name>vehicle</name>
    <occluded>0</occluded>
    <bndbox>
      <xmin>398.232421875</xmin>
      <ymin>143.560546875</ymin>
      <xmax>419.33130264282227</xmax>
      <ymax>160.32214736938477</ymax>
    </bndbox>
  </object>
  <object>
    <name>vehicle</name>
    <occluded>0</occluded>
    <bndbox>
      <xmin>375.208984375</xmin>
      <ymin>144.90000000000146</ymin>
      <xmax>404.40000000000146</xmax>
      <ymax>168.654296875</ymax>
    </bndbox>
  </object>
  <object>
    <name>vehicle</name>
    <occluded>0</occluded>
    <bndbox>
      <xmin>155.0</xmin>
      <ymin>260.90000000000146</ymin>
      <xmax>269.0</xmax>
      <ymax>342.0</ymax>
    </bndbox>
  </object>
  <object>
    <name>vehicle</name>
    <occluded>0</occluded>
    <bndbox>
      <xmin>470.69140625</xmin>
      <ymin>139.29999999999927</ymin>
      <xmax>487.2999999999993</xmax>
      <ymax>152.30859375</ymax>
    </bndbox>
  </object>
  <object>
    <name>vehicle</name>
    <occluded>0</occluded>
    <bndbox>
      <xmin>0.0</xmin>
      <ymin>215.609375</ymin>
      <xmax>24.470155715942383</xmax>
      <ymax>239.70937538146973</ymax>
    </bndbox>
  </object>
</annotation>
