<annotation>
  <folder></folder>
  <filename>007703.jpeg</filename>
  <source>
    <database>Unknown</database>
    <annotation>Unknown</annotation>
    <image>Unknown</image>
  </source>
  <size>
    <width>704</width>
    <height>480</height>
    <depth>3</depth>
  </size>
  <segmented>0</segmented>
  <object>
    <name>vehicle</name>
    <occluded>0</occluded>
    <bndbox>
      <xmin>484.8603515625</xmin>
      <ymin>463.5830078125</ymin>
      <xmax>561.6213912963867</xmax>
      <ymax>480.0</ymax>
    </bndbox>
  </object>
  <object>
    <name>vehicle</name>
    <occluded>0</occluded>
    <bndbox>
      <xmin>338.0205078125</xmin>
      <ymin>396.8212890625</ymin>
      <xmax>393.6533317565918</xmax>
      <ymax>438.54590606689453</ymax>
    </bndbox>
  </object>
  <object>
    <name>vehicle</name>
    <occluded>0</occluded>
    <bndbox>
      <xmin>140.0</xmin>
      <ymin>282.0</ymin>
      <xmax>153.0</xmax>
      <ymax>294.0</ymax>
    </bndbox>
  </object>
  <object>
    <name>vehicle</name>
    <occluded>0</occluded>
    <bndbox>
      <xmin>79.0</xmin>
      <ymin>297.0</ymin>
      <xmax>106.0</xmax>
      <ymax>313.0</ymax>
    </bndbox>
  </object>
  <object>
    <name>vehicle</name>
    <occluded>0</occluded>
    <bndbox>
      <xmin>135.0</xmin>
      <ymin>298.0</ymin>
      <xmax>170.0</xmax>
      <ymax>313.0</ymax>
    </bndbox>
  </object>
  <object>
    <name>vehicle</name>
    <occluded>0</occluded>
    <bndbox>
      <xmin>148.0</xmin>
      <ymin>324.0</ymin>
      <xmax>175.0</xmax>
      <ymax>344.0</ymax>
    </bndbox>
  </object>
  <object>
    <name>vehicle</name>
    <occluded>0</occluded>
    <bndbox>
      <xmin>358.0</xmin>
      <ymin>360.0</ymin>
      <xmax>410.0</xmax>
      <ymax>393.0</ymax>
    </bndbox>
  </object>
  <object>
    <name>vehicle</name>
    <occluded>0</occluded>
    <bndbox>
      <xmin>462.0</xmin>
      <ymin>378.0</ymin>
      <xmax>524.0</xmax>
      <ymax>408.0</ymax>
    </bndbox>
  </object>
  <object>
    <name>vehicle</name>
    <occluded>0</occluded>
    <bndbox>
      <xmin>649.0</xmin>
      <ymin>434.0</ymin>
      <xmax>704.0</xmax>
      <ymax>448.0</ymax>
    </bndbox>
  </object>
  <object>
    <name>pedestrian</name>
    <occluded>0</occluded>
    <bndbox>
      <xmin>32.80000000000109</xmin>
      <ymin>401.3994140625</ymin>
      <xmax>50.0</xmax>
      <ymax>449.99941406249854</ymax>
    </bndbox>
  </object>
  <object>
    <name>pedestrian</name>
    <occluded>0</occluded>
    <bndbox>
      <xmin>31.8505859375</xmin>
      <ymin>380.47265625</ymin>
      <xmax>43.029377937316895</xmax>
      <ymax>411.3261203765869</ymax>
    </bndbox>
  </object>
  <object>
    <name>pedestrian</name>
    <occluded>0</occluded>
    <bndbox>
      <xmin>68.71875</xmin>
      <ymin>387.1796875</ymin>
      <xmax>80.12111759185791</xmax>
      <ymax>414.45594024658203</ymax>
    </bndbox>
  </object>
  <object>
    <name>pedestrian</name>
    <occluded>0</occluded>
    <bndbox>
      <xmin>684.0</xmin>
      <ymin>369.0</ymin>
      <xmax>698.0</xmax>
      <ymax>404.0</ymax>
    </bndbox>
  </object>
  <object>
    <name>bus</name>
    <occluded>0</occluded>
    <bndbox>
      <xmin>341.0</xmin>
      <ymin>306.40000000000146</ymin>
      <xmax>431.0</xmax>
      <ymax>349.0</ymax>
    </bndbox>
  </object>
  <object>
    <name>bus</name>
    <occluded>0</occluded>
    <bndbox>
      <xmin>308.9287109375</xmin>
      <ymin>298.6669921875</ymin>
      <xmax>356.77394104003906</xmax>
      <ymax>329.0733051300049</ymax>
    </bndbox>
  </object>
  <object>
    <name>vehicle</name>
    <occluded>0</occluded>
    <bndbox>
      <xmin>118.7099609375</xmin>
      <ymin>277.23046875</ymin>
      <xmax>127.7099609375</xmax>
      <ymax>283.83046865463257</ymax>
    </bndbox>
  </object>
  <object>
    <name>vehicle</name>
    <occluded>0</occluded>
    <bndbox>
      <xmin>484.0</xmin>
      <ymin>415.7998046875</ymin>
      <xmax>578.1000000000004</xmax>
      <ymax>462.90000000000146</ymax>
    </bndbox>
  </object>
  <object>
    <name>vehicle</name>
    <occluded>0</occluded>
    <bndbox>
      <xmin>384.3000000000011</xmin>
      <ymin>417.40000000000146</ymin>
      <xmax>472.0</xmax>
      <ymax>478.0</ymax>
    </bndbox>
  </object>
  <object>
    <name>vehicle</name>
    <occluded>0</occluded>
    <bndbox>
      <xmin>115.1279296875</xmin>
      <ymin>283.69921875</ymin>
      <xmax>125.70039062500109</xmax>
      <ymax>292.43496093749854</ymax>
    </bndbox>
  </object>
  <object>
    <name>vehicle</name>
    <occluded>0</occluded>
    <bndbox>
      <xmin>273.2392578125</xmin>
      <ymin>327.5517578125</ymin>
      <xmax>301.5592575073242</xmax>
      <ymax>346.63175773620605</ymax>
    </bndbox>
  </object>
  <object>
    <name>vehicle</name>
    <occluded>0</occluded>
    <bndbox>
      <xmin>255.83984375</xmin>
      <ymin>319.8720703125</ymin>
      <xmax>280.91984367370605</xmax>
      <ymax>335.5920705795288</ymax>
    </bndbox>
  </object>
  <object>
    <name>vehicle</name>
    <occluded>0</occluded>
    <bndbox>
      <xmin>308.640625</xmin>
      <ymin>327.9111328125</ymin>
      <xmax>333.48062324523926</xmax>
      <ymax>343.3911323547363</ymax>
    </bndbox>
  </object>
  <object>
    <name>vehicle</name>
    <occluded>0</occluded>
    <bndbox>
      <xmin>225.2353515625</xmin>
      <ymin>307.474609375</ymin>
      <xmax>233.19797563552856</xmax>
      <ymax>321.6580333709717</ymax>
    </bndbox>
  </object>
  <object>
    <name>vehicle</name>
    <occluded>0</occluded>
    <bndbox>
      <xmin>268.9208984375</xmin>
      <ymin>292.7529296875</ymin>
      <xmax>308.7608985900879</xmax>
      <ymax>327.312931060791</ymax>
    </bndbox>
  </object>
  <object>
    <name>vehicle</name>
    <occluded>0</occluded>
    <bndbox>
      <xmin>117.6103515625</xmin>
      <ymin>273.40000000000146</ymin>
      <xmax>124.31035137176514</xmax>
      <ymax>279.83027362823486</ymax>
    </bndbox>
  </object>
  <object>
    <name>vehicle</name>
    <occluded>0</occluded>
    <bndbox>
      <xmin>231.7197265625</xmin>
      <ymin>294.5517578125</ymin>
      <xmax>268.67972564697266</xmax>
      <ymax>326.3517589569092</ymax>
    </bndbox>
  </object>
  <object>
    <name>vehicle</name>
    <occluded>0</occluded>
    <bndbox>
      <xmin>123.4765625</xmin>
      <ymin>281.5</ymin>
      <xmax>134.04902362823486</xmax>
      <ymax>287.5804681777954</ymax>
    </bndbox>
  </object>
  <object>
    <name>vehicle</name>
    <occluded>0</occluded>
    <bndbox>
      <xmin>124.4765625</xmin>
      <ymin>271.3000000000011</ymin>
      <xmax>134.70000000000073</xmax>
      <ymax>276.65175771713257</ymax>
    </bndbox>
  </object>
</annotation>
