<annotation>
  <folder></folder>
  <filename>009198.jpeg</filename>
  <source>
    <database>Unknown</database>
    <annotation>Unknown</annotation>
    <image>Unknown</image>
  </source>
  <size>
    <width>352</width>
    <height>240</height>
    <depth>3</depth>
  </size>
  <segmented>0</segmented>
  <object>
    <name>vehicle</name>
    <occluded>0</occluded>
    <bndbox>
      <xmin>47.0</xmin>
      <ymin>196.0</ymin>
      <xmax>107.0</xmax>
      <ymax>240.0</ymax>
    </bndbox>
  </object>
  <object>
    <name>vehicle</name>
    <occluded>0</occluded>
    <bndbox>
      <xmin>164.0</xmin>
      <ymin>126.29999999999927</ymin>
      <xmax>185.20000000000073</xmax>
      <ymax>142.0</ymax>
    </bndbox>
  </object>
  <object>
    <name>vehicle</name>
    <occluded>0</occluded>
    <bndbox>
      <xmin>198.0</xmin>
      <ymin>94.20000000000073</ymin>
      <xmax>204.29999999999927</xmax>
      <ymax>99.0</ymax>
    </bndbox>
  </object>
  <object>
    <name>vehicle</name>
    <occluded>0</occluded>
    <bndbox>
      <xmin>343.572265625</xmin>
      <ymin>124.26953125</ymin>
      <xmax>351.6701250076294</xmax>
      <ymax>137.72518920898438</ymax>
    </bndbox>
  </object>
  <object>
    <name>vehicle</name>
    <occluded>0</occluded>
    <bndbox>
      <xmin>167.0</xmin>
      <ymin>181.0</ymin>
      <xmax>183.0</xmax>
      <ymax>209.0</ymax>
    </bndbox>
  </object>
  <object>
    <name>vehicle</name>
    <occluded>0</occluded>
    <bndbox>
      <xmin>250.0</xmin>
      <ymin>96.0</ymin>
      <xmax>257.0</xmax>
      <ymax>102.0</ymax>
    </bndbox>
  </object>
  <object>
    <name>vehicle</name>
    <occluded>0</occluded>
    <bndbox>
      <xmin>122.41015625</xmin>
      <ymin>131.853515625</ymin>
      <xmax>146.8749885559082</xmax>
      <ymax>152.8932704925537</ymax>
    </bndbox>
  </object>
  <object>
    <name>vehicle</name>
    <occluded>0</occluded>
    <bndbox>
      <xmin>64.0</xmin>
      <ymin>155.0</ymin>
      <xmax>105.0</xmax>
      <ymax>185.0</ymax>
    </bndbox>
  </object>
  <object>
    <name>vehicle</name>
    <occluded>0</occluded>
    <bndbox>
      <xmin>303.0</xmin>
      <ymin>141.0</ymin>
      <xmax>330.0</xmax>
      <ymax>161.0</ymax>
    </bndbox>
  </object>
  <object>
    <name>vehicle</name>
    <occluded>0</occluded>
    <bndbox>
      <xmin>135.69921875</xmin>
      <ymin>144.0</ymin>
      <xmax>162.29999999999927</xmax>
      <ymax>169.0</ymax>
    </bndbox>
  </object>
  <object>
    <name>vehicle</name>
    <occluded>0</occluded>
    <bndbox>
      <xmin>183.107421875</xmin>
      <ymin>113.7734375</ymin>
      <xmax>195.3398380279541</xmax>
      <ymax>125.49209213256836</ymax>
    </bndbox>
  </object>
  <object>
    <name>vehicle</name>
    <occluded>0</occluded>
    <bndbox>
      <xmin>171.583984375</xmin>
      <ymin>117.443359375</ymin>
      <xmax>187.99988746643066</xmax>
      <ymax>129.16201400756836</ymax>
    </bndbox>
  </object>
  <object>
    <name>pedestrian</name>
    <occluded>0</occluded>
    <bndbox>
      <xmin>23.81640625</xmin>
      <ymin>159.498046875</ymin>
      <xmax>33.1130428314209</xmax>
      <ymax>182.98428535461426</ymax>
    </bndbox>
  </object>
</annotation>
