<annotation>
  <folder></folder>
  <filename>009134.jpeg</filename>
  <source>
    <database>Unknown</database>
    <annotation>Unknown</annotation>
    <image>Unknown</image>
  </source>
  <size>
    <width>352</width>
    <height>240</height>
    <depth>3</depth>
  </size>
  <segmented>0</segmented>
  <object>
    <name>vehicle</name>
    <occluded>0</occluded>
    <bndbox>
      <xmin>252.23046875</xmin>
      <ymin>89.099609375</ymin>
      <xmax>256.43046855926514</xmax>
      <ymax>92.19960927963257</ymax>
    </bndbox>
  </object>
  <object>
    <name>vehicle</name>
    <occluded>0</occluded>
    <bndbox>
      <xmin>254.51953125</xmin>
      <ymin>90.287109375</ymin>
      <xmax>259.6816110610962</xmax>
      <ymax>93.95683407783508</ymax>
    </bndbox>
  </object>
  <object>
    <name>vehicle</name>
    <occluded>0</occluded>
    <bndbox>
      <xmin>257.2109375</xmin>
      <ymin>92.46484375</ymin>
      <xmax>263.5717935562134</xmax>
      <ymax>96.64832973480225</ymax>
    </bndbox>
  </object>
  <object>
    <name>vehicle</name>
    <occluded>0</occluded>
    <bndbox>
      <xmin>260.146484375</xmin>
      <ymin>93.95703125</ymin>
      <xmax>267.0211019515991</xmax>
      <ymax>98.0915880203247</ymax>
    </bndbox>
  </object>
  <object>
    <name>vehicle</name>
    <occluded>0</occluded>
    <bndbox>
      <xmin>343.572265625</xmin>
      <ymin>123.53515625</ymin>
      <xmax>351.40101146698</xmax>
      <ymax>135.7675724029541</ymax>
    </bndbox>
  </object>
  <object>
    <name>vehicle</name>
    <occluded>0</occluded>
    <bndbox>
      <xmin>283.90234375</xmin>
      <ymin>99.0703125</ymin>
      <xmax>303.2050971984863</xmax>
      <ymax>107.1681718826294</ymax>
    </bndbox>
  </object>
  <object>
    <name>vehicle</name>
    <occluded>0</occluded>
    <bndbox>
      <xmin>292.46484375</xmin>
      <ymin>102.275390625</ymin>
      <xmax>306.8746290206909</xmax>
      <ymax>109.10107898712158</ymax>
    </bndbox>
  </object>
  <object>
    <name>vehicle</name>
    <occluded>0</occluded>
    <bndbox>
      <xmin>313.259765625</xmin>
      <ymin>108.3671875</ymin>
      <xmax>347.730712890625</xmax>
      <ymax>122.55679035186768</ymax>
    </bndbox>
  </object>
  <object>
    <name>vehicle</name>
    <occluded>0</occluded>
    <bndbox>
      <xmin>197.0</xmin>
      <ymin>91.5</ymin>
      <xmax>204.79999999999927</xmax>
      <ymax>98.0</ymax>
    </bndbox>
  </object>
  <object>
    <name>vehicle</name>
    <occluded>0</occluded>
    <bndbox>
      <xmin>262.5</xmin>
      <ymin>96.60000000000218</ymin>
      <xmax>272.0</xmax>
      <ymax>102.0</ymax>
    </bndbox>
  </object>
  <object>
    <name>vehicle</name>
    <occluded>0</occluded>
    <bndbox>
      <xmin>216.900390625</xmin>
      <ymin>92.69921875</ymin>
      <xmax>225.00039062499854</xmax>
      <ymax>99.0</ymax>
    </bndbox>
  </object>
  <object>
    <name>vehicle</name>
    <occluded>0</occluded>
    <bndbox>
      <xmin>66.791015625</xmin>
      <ymin>99.63671875</ymin>
      <xmax>81.72093486785889</xmax>
      <ymax>105.90728521347046</ymax>
    </bndbox>
  </object>
  <object>
    <name>vehicle</name>
    <occluded>0</occluded>
    <bndbox>
      <xmin>336.501953125</xmin>
      <ymin>118.88671875</ymin>
      <xmax>350.6915559768677</xmax>
      <ymax>129.16194820404053</ymax>
    </bndbox>
  </object>
  <object>
    <name>vehicle</name>
    <occluded>0</occluded>
    <bndbox>
      <xmin>207.23046875</xmin>
      <ymin>87.599609375</ymin>
      <xmax>212.73046875</xmax>
      <ymax>92.19960927963257</ymax>
    </bndbox>
  </object>
  <object>
    <name>vehicle</name>
    <occluded>0</occluded>
    <bndbox>
      <xmin>203.12890625</xmin>
      <ymin>89.69921875</ymin>
      <xmax>208.72890615463257</xmax>
      <ymax>94.09921884536743</ymax>
    </bndbox>
  </object>
  <object>
    <name>vehicle</name>
    <occluded>0</occluded>
    <bndbox>
      <xmin>215.330078125</xmin>
      <ymin>88.900390625</ymin>
      <xmax>221.23007822036743</xmax>
      <ymax>93.50039052963257</ymax>
    </bndbox>
  </object>
  <object>
    <name>construction</name>
    <occluded>0</occluded>
    <bndbox>
      <xmin>103.12890625</xmin>
      <ymin>135.0</ymin>
      <xmax>107.01890635490417</xmax>
      <ymax>143.60000038146973</ymax>
    </bndbox>
  </object>
  <object>
    <name>construction</name>
    <occluded>0</occluded>
    <bndbox>
      <xmin>105.73046875</xmin>
      <ymin>133.599609375</ymin>
      <xmax>110.23046875</xmax>
      <ymax>142.49960899353027</ymax>
    </bndbox>
  </object>
  <object>
    <name>construction</name>
    <occluded>0</occluded>
    <bndbox>
      <xmin>99.23046875</xmin>
      <ymin>135.19921875</ymin>
      <xmax>103.63046884536743</xmax>
      <ymax>144.19921875</ymax>
    </bndbox>
  </object>
</annotation>
