<annotation>
  <folder></folder>
  <filename>009430.jpeg</filename>
  <source>
    <database>Unknown</database>
    <annotation>Unknown</annotation>
    <image>Unknown</image>
  </source>
  <size>
    <width>352</width>
    <height>240</height>
    <depth>3</depth>
  </size>
  <segmented>0</segmented>
  <object>
    <name>vehicle</name>
    <occluded>0</occluded>
    <bndbox>
      <xmin>112.0244140625</xmin>
      <ymin>100.30000000000109</ymin>
      <xmax>151.70000000000073</xmax>
      <ymax>125.7958984375</ymax>
    </bndbox>
  </object>
  <object>
    <name>vehicle</name>
    <occluded>0</occluded>
    <bndbox>
      <xmin>261.0</xmin>
      <ymin>70.0</ymin>
      <xmax>273.0</xmax>
      <ymax>80.0</ymax>
    </bndbox>
  </object>
  <object>
    <name>vehicle</name>
    <occluded>0</occluded>
    <bndbox>
      <xmin>239.681640625</xmin>
      <ymin>77.20000000000073</ymin>
      <xmax>250.5</xmax>
      <ymax>85.322265625</ymax>
    </bndbox>
  </object>
  <object>
    <name>vehicle</name>
    <occluded>0</occluded>
    <bndbox>
      <xmin>152.2490234375</xmin>
      <ymin>90.267578125</ymin>
      <xmax>184.87954711914062</xmax>
      <ymax>111.68658828735352</ymax>
    </bndbox>
  </object>
  <object>
    <name>vehicle</name>
    <occluded>0</occluded>
    <bndbox>
      <xmin>184.544921875</xmin>
      <ymin>88.259765625</ymin>
      <xmax>214.49806785583496</xmax>
      <ymax>102.9853343963623</ymax>
    </bndbox>
  </object>
</annotation>
